vector_me/cli.py
vector_me/plugins/base.py
vector_me/plugins/chunkers/recursive.py
vector_me/plugins/embedders/huggingface.py
vector_me/plugins/embedders/openai.py
vector_me/plugins/vector_stores/chroma.py
vector_me/plugins/vector_stores/faiss.py
vector_me/plugins/vector_stores/qdrant.py
vector_me-0.1.0.dist-info/METADATA
vector_me-0.1.0.dist-info/WHEEL
vector_me-0.1.0.dist-info/RECORD
