Metadata-Version: 2.4
Name: vector-me
Version: 0.1.0
Summary: A flexible vector database builder with plugin support
Author-email: TheDataGuy <me@thedataguy.pro>
License: MIT
Requires-Python: >=3.9
Requires-Dist: chromadb>=0.4.0
Requires-Dist: faiss-cpu>=1.7.4
Requires-Dist: langchain>=0.1.0
Requires-Dist: langgraph>=0.0.10
Requires-Dist: openai>=1.0.0
Requires-Dist: pydantic>=2.0.0
Requires-Dist: qdrant-client>=1.7.0
Requires-Dist: rich>=13.0.0
Requires-Dist: sentence-transformers>=2.2.2
Requires-Dist: typer>=0.9.0
Provides-Extra: dev
Requires-Dist: black>=23.0.0; extra == 'dev'
Requires-Dist: mypy>=1.0.0; extra == 'dev'
Requires-Dist: pytest-cov>=4.0.0; extra == 'dev'
Requires-Dist: pytest>=7.0.0; extra == 'dev'
Requires-Dist: ruff>=0.1.0; extra == 'dev'
